[{"type": "price_level", "name": "双环传动", "current_percent": 0.8905031515805591, "n_day": 17, "highest_flag": false}, {"type": "price_level", "name": "水晶光电", "current_percent": 0.9876089342393869, "n_day": 2, "highest_flag": false}, {"type": "price_level", "name": "北方华创", "current_percent": 0.9684300295651448, "n_day": 1, "highest_flag": false}, {"type": "price_level", "name": "江苏金租", "current_percent": 0.9627162673463148, "n_day": 21, "highest_flag": false}, {"type": "price_level", "name": "格力电器", "current_percent": 0.44454492641806553, "n_day": 359, "highest_flag": false}, {"type": "price_level", "name": "北京银行", "current_percent": 0.5396798620661512, "n_day": 1, "highest_flag": true}, {"type": "price_level", "name": "亨通光电", "current_percent": 1.0, "n_day": 2768, "highest_flag": true}, {"type": "price_level", "name": "首创环保", "current_percent": 0.8817718320527407, "n_day": 100, "highest_flag": true}, {"type": "price_level", "name": "中国海油", "current_percent": 0.9929643462761744, "n_day": 2, "highest_flag": false}, {"type": "price_level", "name": "中国平安", "current_percent": 0.8606265407137412, "n_day": 76, "highest_flag": false}, {"type": "price_level", "name": "中兴通讯", "current_percent": 0.7778671502032157, "n_day": 27, "highest_flag": true}, {"type": "price_level", "name": "大族激光", "current_percent": 1.0, "n_day": 2753, "highest_flag": true}, {"type": "price_level", "name": "美的集团", "current_percent": 0.9442807513567353, "n_day": 2, "highest_flag": false}, {"type": "price_level", "name": "三星医疗", "current_percent": 0.7388904062779765, "n_day": 36, "highest_flag": true}, {"type": "price_level", "name": "移远通信", "current_percent": 0.686317942184802, "n_day": 14, "highest_flag": true}, {"type": "price_level", "name": "比亚迪", "current_percent": 0.4584833082951676, "n_day": 17, "highest_flag": false}, {"type": "price_level", "name": "公牛集团", "current_percent": 0.2050049033962297, "n_day": 2, "highest_flag": false}, {"type": "price_level", "name": "歌尔股份", "current_percent": 0.6313621809822145, "n_day": 29, "highest_flag": true}, {"type": "price_level", "name": "三七互娱", "current_percent": 0.8537773590863295, "n_day": 52, "highest_flag": false}, {"type": "price_level", "name": "平安银行", "current_percent": 0.3936385148190408, "n_day": 275, "highest_flag": false}, {"type": "price_level", "name": "瑞芯微", "current_percent": 0.8592751861393457, "n_day": 1, "highest_flag": true}, {"type": "price_level", "name": "国网英大", "current_percent": 0.9824183466604552, "n_day": 1505, "highest_flag": true}, {"type": "price_level", "name": "兆威机电", "current_percent": 0.8117916390023422, "n_day": 20, "highest_flag": false}, {"type": "price_level", "name": "埃斯顿", "current_percent": 0.7678154619590982, "n_day": 16, "highest_flag": false}, {"type": "price_level", "name": "金地集团", "current_percent": 0.10973033867574117, "n_day": 22, "highest_flag": false}]