[{"type": "price_level", "name": "双环传动", "current_percent": 0.9186475083720008, "n_day": 34, "highest_flag": false}, {"type": "price_level", "name": "水晶光电", "current_percent": 0.8781727356267787, "n_day": 28, "highest_flag": false}, {"type": "price_level", "name": "北方华创", "current_percent": 0.9736574855448343, "n_day": 13, "highest_flag": false}, {"type": "price_level", "name": "江苏金租", "current_percent": 0.9453889815695703, "n_day": 5, "highest_flag": true}, {"type": "price_level", "name": "格力电器", "current_percent": 0.47947856734683997, "n_day": 321, "highest_flag": false}, {"type": "price_level", "name": "北京银行", "current_percent": 0.5217532229338641, "n_day": 5, "highest_flag": true}, {"type": "price_level", "name": "亨通光电", "current_percent": 1.0, "n_day": 2760, "highest_flag": true}, {"type": "price_level", "name": "首创环保", "current_percent": 0.8283691675329796, "n_day": 71, "highest_flag": true}, {"type": "price_level", "name": "中国海油", "current_percent": 1.0, "n_day": 1378, "highest_flag": true}, {"type": "price_level", "name": "中国平安", "current_percent": 0.9001012055726001, "n_day": 1, "highest_flag": false}, {"type": "price_level", "name": "中兴通讯", "current_percent": 0.824187080830902, "n_day": 1, "highest_flag": false}, {"type": "price_level", "name": "大族激光", "current_percent": 0.9970950730418325, "n_day": 1, "highest_flag": false}, {"type": "price_level", "name": "美的集团", "current_percent": 0.864457387986039, "n_day": 83, "highest_flag": false}, {"type": "price_level", "name": "三星医疗", "current_percent": 0.6720678049858005, "n_day": 1, "highest_flag": true}, {"type": "price_level", "name": "移远通信", "current_percent": 0.8520640013638351, "n_day": 1, "highest_flag": false}, {"type": "price_level", "name": "比亚迪", "current_percent": 0.4833589465499746, "n_day": 357, "highest_flag": false}, {"type": "price_level", "name": "公牛集团", "current_percent": 0.043378566428368966, "n_day": 19, "highest_flag": false}, {"type": "price_level", "name": "歌尔股份", "current_percent": 0.6201240766822214, "n_day": 163, "highest_flag": false}, {"type": "price_level", "name": "三七互娱", "current_percent": 0.9147371730760416, "n_day": 21, "highest_flag": false}, {"type": "price_level", "name": "平安银行", "current_percent": 0.45186891023608416, "n_day": 243, "highest_flag": false}, {"type": "price_level", "name": "瑞芯微", "current_percent": 0.9590563795091174, "n_day": 106, "highest_flag": true}, {"type": "price_level", "name": "国网英大", "current_percent": 0.9638728356850457, "n_day": 1, "highest_flag": true}, {"type": "price_level", "name": "兆威机电", "current_percent": 0.8530577421385799, "n_day": 1, "highest_flag": false}, {"type": "price_level", "name": "埃斯顿", "current_percent": 0.7989771127856681, "n_day": 16, "highest_flag": false}, {"type": "price_level", "name": "金地集团", "current_percent": 0.03873778729904137, "n_day": 1, "highest_flag": true}]